tests/__init__.py
tests/test_корни_кв_уравнения.py
tests/test_радиус.py
Заур__Илья/__init__.py
Заур__Илья/корни_кв_уравнения.py
Заур__Илья/радиус.py
geometryhelper-0.1.0.dist-info/METADATA
geometryhelper-0.1.0.dist-info/WHEEL
geometryhelper-0.1.0.dist-info/top_level.txt
geometryhelper-0.1.0.dist-info/RECORD
